troposphere/__init__.py
troposphere/accessanalyzer.py
troposphere/acmpca.py
troposphere/aiops.py
troposphere/amazonmq.py
troposphere/amplify.py
troposphere/analytics.py
troposphere/apigateway.py
troposphere/apigatewayv2.py
troposphere/appconfig.py
troposphere/appflow.py
troposphere/appintegrations.py
troposphere/applicationautoscaling.py
troposphere/applicationinsights.py
troposphere/applicationsignals.py
troposphere/appmesh.py
troposphere/apprunner.py
troposphere/appstream.py
troposphere/appsync.py
troposphere/apptest.py
troposphere/aps.py
troposphere/arczonalshift.py
troposphere/ask.py
troposphere/athena.py
troposphere/auditmanager.py
troposphere/autoscaling.py
troposphere/autoscalingplans.py
troposphere/awslambda.py
troposphere/b2bi.py
troposphere/backup.py
troposphere/backupgateway.py
troposphere/batch.py
troposphere/bcmdataexports.py
troposphere/bedrock.py
troposphere/bedrockagentcore.py
troposphere/billing.py
troposphere/billingconductor.py
troposphere/budgets.py
troposphere/cassandra.py
troposphere/ce.py
troposphere/certificatemanager.py
troposphere/chatbot.py
troposphere/cleanrooms.py
troposphere/cleanroomsml.py
troposphere/cloud9.py
troposphere/cloudformation.py
troposphere/cloudfront.py
troposphere/cloudtrail.py
troposphere/cloudwatch.py
troposphere/codeartifact.py
troposphere/codebuild.py
troposphere/codecommit.py
troposphere/codeconnections.py
troposphere/codedeploy.py
troposphere/codeguruprofiler.py
troposphere/codegurureviewer.py
troposphere/codepipeline.py
troposphere/codestar.py
troposphere/codestarconnections.py
troposphere/codestarnotifications.py
troposphere/cognito.py
troposphere/compat.py
troposphere/comprehend.py
troposphere/config.py
troposphere/connect.py
troposphere/connectcampaigns.py
troposphere/connectcampaignsv2.py
troposphere/constants.py
troposphere/controltower.py
troposphere/cur.py
troposphere/customerprofiles.py
troposphere/databrew.py
troposphere/datapipeline.py
troposphere/datasync.py
troposphere/datazone.py
troposphere/dax.py
troposphere-4.9.6.dist-info/licenses/LICENSE
troposphere-4.9.6.dist-info/METADATA
troposphere-4.9.6.dist-info/WHEEL
troposphere-4.9.6.dist-info/top_level.txt
troposphere-4.9.6.dist-info/RECORD
