Metadata-Version: 2.4
Name: troposphere
Version: 4.9.6
Summary: AWS CloudFormation creation library
Home-page: https://github.com/cloudtools/troposphere
Author: Mark Peek
Author-email: mark@peek.org
License: New BSD license
Project-URL: Changelog, https://github.com/cloudtools/troposphere/blob/master/CHANGELOG.md
Project-URL: Source, https://github.com/cloudtools/troposphere
Project-URL: Tracker, https://github.com/cloudtools/troposphere/issues
Classifier: Development Status :: 5 - Production/Stable
Classifier: Intended Audience :: Developers
Classifier: License :: OSI Approved :: BSD License
Classifier: Operating System :: OS Independent
Classifier: Programming Language :: Python
Classifier: Programming Language :: Python :: 3 :: Only
Classifier: Programming Language :: Python :: 3
Classifier: Programming Language :: Python :: 3.9
Classifier: Programming Language :: Python :: 3.10
Classifier: Programming Language :: Python :: 3.11
Classifier: Programming Language :: Python :: 3.12
Classifier: Programming Language :: Python :: 3.13
Classifier: Programming Language :: Python :: 3.14
Requires-Python: >=3.8
License-File: LICENSE
Requires-Dist: cfn_flip>=1.0.2
Provides-Extra: policy
Requires-Dist: awacs>=2.0.0; extra == "policy"
Dynamic: license-file
